pahelix/__init__.py
pahelix/cmdline.py
pahelix/datasets/__init__.py
pahelix/datasets/bace_dataset.py
pahelix/datasets/bbbp_dataset.py
pahelix/datasets/chembl_filtered_dataset.py
pahelix/datasets/clintox_dataset.py
pahelix/datasets/davis_dataset.py
pahelix/datasets/ddi_dataset.py
pahelix/datasets/dti_dataset.py
pahelix/datasets/esol_dataset.py
pahelix/datasets/freesolv_dataset.py
pahelix/datasets/hiv_dataset.py
pahelix/datasets/inmemory_dataset.py
pahelix/datasets/kiba_dataset.py
pahelix/datasets/lipophilicity_dataset.py
pahelix/datasets/mutag_dataset.py
pahelix/datasets/muv_dataset.py
pahelix/datasets/ogbg_molhiv_dataset.py
pahelix/datasets/ogbg_molpcba_dataset.py
pahelix/datasets/pdbbind_dataset.py
pahelix/datasets/ppi_dataset.py
pahelix/datasets/ptc_mr_dataset.py
pahelix/datasets/sider_dataset.py
pahelix/datasets/tox21_dataset.py
pahelix/datasets/toxcast_dataset.py
pahelix/datasets/zinc_dataset.py
pahelix/featurizers/__init__.py
pahelix/featurizers/het_gnn_featurizer.py
pahelix/featurizers/pretrain_gnn_featurizer.py
pahelix/model_zoo/__init__.py
pahelix/model_zoo/pretrain_gnns_model.py
pahelix/model_zoo/protein_sequence_model.py
pahelix/model_zoo/sd_vae_model.py
pahelix/model_zoo/seq_vae_model.py
pahelix/networks/__init__.py
pahelix/networks/basic_block.py
pahelix/networks/compound_encoder.py
pahelix/networks/gnn_block.py
pahelix/networks/involution_block.py
pahelix/networks/lstm_block.py
pahelix/networks/optimizer.py
pahelix/networks/pre_post_process.py
pahelix/networks/resnet_block.py
pahelix/networks/transformer_block.py
pahelix/tests/__init__.py
pahelix/tests/import_test.py
pahelix/toolkit/linear_rna.cpython-38-darwin.so
pahelix/utils/__init__.py
pahelix/utils/basic_utils.py
pahelix/utils/compound_tools.py
pahelix/utils/data_utils.py
pahelix/utils/language_model_tools.py
pahelix/utils/protein_tools.py
pahelix/utils/splitters.py
paddlehelix-1.0.1.dist-info/LICENSE
paddlehelix-1.0.1.dist-info/METADATA
paddlehelix-1.0.1.dist-info/WHEEL
paddlehelix-1.0.1.dist-info/top_level.txt
paddlehelix-1.0.1.dist-info/RECORD
